protectron/__init__.py
protectron/buffer.py
protectron/client.py
protectron/config.py
protectron/context.py
protectron/decorators.py
protectron/events.py
protectron/exceptions.py
protectron/hitl.py
protectron/integrations/__init__.py
protectron/integrations/base.py
protectron/integrations/crewai.py
protectron/integrations/langchain.py
protectron/transport.py
protectron/utils/__init__.py
protectron/utils/ids.py
protectron/utils/pii.py
protectron-0.1.0.dist-info/METADATA
protectron-0.1.0.dist-info/WHEEL
protectron-0.1.0.dist-info/licenses/LICENSE
protectron-0.1.0.dist-info/RECORD
