Metadata-Version: 2.4
Name: protectron
Version: 0.1.0
Summary: EU AI Act compliance SDK for AI agents - Automatic audit logging, HITL approvals, and evidence generation
License: MIT
License-File: LICENSE
Keywords: ai,compliance,eu-ai-act,audit,langchain,crewai,agents
Author: Protectron Team
Author-email: team@protectron.ai
Requires-Python: >=3.9,<4.0
Classifier: Development Status :: 4 - Beta
Classifier: Intended Audience :: Developers
Classifier: License :: OSI Approved :: MIT License
Classifier: Programming Language :: Python :: 3
Classifier: Programming Language :: Python :: 3.9
Classifier: Programming Language :: Python :: 3.10
Classifier: Programming Language :: Python :: 3.11
Classifier: Programming Language :: Python :: 3.12
Classifier: Programming Language :: Python :: 3.13
Classifier: Programming Language :: Python :: 3.14
Classifier: Topic :: Scientific/Engineering :: Artificial Intelligence
Classifier: Topic :: Software Development :: Libraries :: Python Modules
Requires-Dist: requests (>=2.32.0,<3.0.0)
Requires-Dist: typing-extensions (>=4.12.0,<5.0.0)
Project-URL: Homepage, https://protectron.ai
Project-URL: Repository, https://github.com/protectron-ai/protectron-sdk
